jobstorm/__init__.py
jobstorm/_version.py
jobstorm/jobcode.py
jupyter_jobstorm-0.4.0.dist-info/LICENSE
jupyter_jobstorm-0.4.0.dist-info/METADATA
jupyter_jobstorm-0.4.0.dist-info/WHEEL
jupyter_jobstorm-0.4.0.dist-info/top_level.txt
jupyter_jobstorm-0.4.0.dist-info/RECORD
