Metadata-Version: 2.1
Name: jupyter-jobstorm
Version: 0.4.0
Summary: A tool to run a function written in Jupyter cell as a job
Home-page: https://github.com/schrodingers-koala/jupyter-jobstorm
Author: schrodingers-koala
Author-email: schrodingers.koala@gmail.com
License: MIT
Keywords: jupyter-jobstorm,jobstorm
Classifier: License :: OSI Approved :: MIT License
Classifier: Programming Language :: Python :: 3
Classifier: Programming Language :: Python :: 3.7
Classifier: Programming Language :: Python :: 3.8
Classifier: Programming Language :: Python :: 3.9
Classifier: Programming Language :: Python :: 3.10
License-File: LICENSE
Requires-Dist: dill
Requires-Dist: python-jenkins
Requires-Dist: tabulate
